INSTALL.rst
MANIFEST.in
README.rst
VERSION
setup.py
py2src/generic/__init__.py
py2src/generic/conversion.py
py2src/generic/core.py
py2src/generic/errors.py
py2src/generic/fasttrack.py
py2src/generic/meta.py
py2src/generic/op.py
py2src/generic/tree.py
py2src/generic/util.py
py2src/generic/parametric/__init__.py
py2src/generic/parametric/base.py
py2src/generic/parametric/containers.py
py2src/generic/parametric/pytyping.py
py2src/generic/parametric/typeparams.py
py2src/generic/tests/test_conversions.py
py2src/generic/tests/test_core.py
py2src/generic/tests/test_dispatch.py
py2src/generic/tests/test_documentation.py
py2src/generic/tests/test_operator.py
py2src/generic/tests/test_parametric.py
py2src/src/generic/__init__.py
py2src/src/generic/conversion.py
py2src/src/generic/core.py
py2src/src/generic/errors.py
py2src/src/generic/fasttrack.py
py2src/src/generic/meta.py
py2src/src/generic/op.py
py2src/src/generic/tree.py
py2src/src/generic/util.py
py2src/src/generic/parametric/__init__.py
py2src/src/generic/parametric/base.py
py2src/src/generic/parametric/containers.py
py2src/src/generic/parametric/pytyping.py
py2src/src/generic/parametric/typeparams.py
py2src/src/generic/tests/__init__.py
py2src/src/generic/tests/test_conversions.py
py2src/src/generic/tests/test_core.py
py2src/src/generic/tests/test_dispatch.py
py2src/src/generic/tests/test_documentation.py
py2src/src/generic/tests/test_operator.py
py2src/src/generic/tests/test_parametric.py
py2src/src/pygeneric/__init__.py
py2src/src/pygeneric/__main__.py
py2src/src/pygeneric/__meta__.py
py2src/src/pygeneric/tests/__init__.py
py2src/src/pygeneric/tests/__main__.py
py2src/src/pygeneric/tests/test_documentation.py
py2src/src/pygeneric/tests/test_pygeneric.py
src/generic/__init__.py
src/generic/__main__.py
src/generic/__meta__.py
src/generic/conversion.py
src/generic/core.py
src/generic/core_fast.c
src/generic/errors.py
src/generic/fasttrack.py
src/generic/op.py
src/generic/tree.py
src/generic/util.py
src/pygeneric.egg-info/PKG-INFO
src/pygeneric.egg-info/SOURCES.txt
src/pygeneric.egg-info/dependency_links.txt
src/pygeneric.egg-info/not-zip-safe
src/pygeneric.egg-info/requires.txt
src/pygeneric.egg-info/top_level.txt